aws_sec_graph/__init__.py
aws_sec_graph/analyze.py
aws_sec_graph/aws/__init__.py
aws_sec_graph/aws/ec2.py
aws_sec_graph/aws/security_groups.py
aws_sec_graph/graphviz/__init__.py
aws_sec_graph/graphviz/generate_graph.py
aws_sec_graph-0.0.1.dist-info/LICENSE
aws_sec_graph-0.0.1.dist-info/METADATA
aws_sec_graph-0.0.1.dist-info/WHEEL
aws_sec_graph-0.0.1.dist-info/entry_points.txt
aws_sec_graph-0.0.1.dist-info/top_level.txt
aws_sec_graph-0.0.1.dist-info/RECORD
