Metadata-Version: 2.1
Name: aws-sec-graph
Version: 0.0.1
Summary: A AWS Security graph generator
Home-page: UNKNOWN
Author: Gabriel Mourão
Author-email: gabrielmouraodemelo@gmail.com
License: UNKNOWN
Platform: UNKNOWN
Requires-Python: >=3.6
Requires-Dist: boto3
Requires-Dist: packaging
